tempest_weather_collector/__init__.py
tempest_weather_collector/tempest.py
TempestCollector-0.0.13.dist-info/METADATA
TempestCollector-0.0.13.dist-info/WHEEL
TempestCollector-0.0.13.dist-info/top_level.txt
TempestCollector-0.0.13.dist-info/RECORD
